{
    "bb": [
        51.2172068072333,
        10.5413818359375,
        52.8060822398588,
        12.6287841796875
    ],
    "graph": {
        "0": {
            "pos": [
                10.666055903693431,
                51.23683975815584
            ],
            "adj": [
                22,
                1
            ]
        },
        "1": {
            "pos": [
                10.675624289481728,
                51.357390078134905
            ],
            "adj": [
                2,
                28,
                22,
                0
            ]
        },
        "2": {
            "pos": [
                10.644676972208122,
                51.56051942491856
            ],
            "adj": [
                3,
                5,
                17,
                19,
                26,
                1
            ]
        },
        "3": {
            "pos": [
                10.561279809547678,
                51.71681079383471
            ],
            "adj": [
                4,
                5,
                2
            ]
        },
        "4": {
            "pos": [
                10.54447428385416,
                51.777786093273505
            ],
            "adj": [
                5,
                3
            ]
        },
        "5": {
            "pos": [
                10.660963366192846,
                51.825186578673595
            ],
            "adj": [
                6,
                7,
                9,
                27,
                17,
                2,
                3,
                4
            ]
        },
        "6": {
            "pos": [
                10.548955051262302,
                51.8808331619272
            ],
            "adj": [
                7,
                5
            ]
        },
        "7": {
            "pos": [
                10.55809449523238,
                51.93783779310805
            ],
            "adj": [
                8,
                9,
                5,
                6
            ]
        },
        "8": {
            "pos": [
                10.55255849199951,
                51.9729556830078
            ],
            "adj": [
                9,
                7
            ]
        },
        "9": {
            "pos": [
                10.697357497771236,
                51.98073295910443
            ],
            "adj": [
                10,
                21,
                25,
                5,
                7,
                8
            ]
        },
        "10": {
            "pos": [
                10.599975072049732,
                52.0910528522494
            ],
            "adj": [
                11,
                9
            ]
        },
        "11": {
            "pos": [
                10.750905607782745,
                52.18854758889077
            ],
            "adj": [
                12,
                20,
                34,
                29,
                21,
                10
            ]
        },
        "12": {
            "pos": [
                10.633020758332387,
                52.2777337568037
            ],
            "adj": [
                18,
                20,
                11,
                13
            ]
        },
        "13": {
            "pos": [
                10.570678373166842,
                52.2976189923706
            ],
            "adj": [
                14,
                12
            ]
        },
        "14": {
            "pos": [
                10.625585413107,
                52.40476332811519
            ],
            "adj": [
                15,
                23,
                18,
                13
            ]
        },
        "15": {
            "pos": [
                10.688117040520174,
                52.608203838681675
            ],
            "adj": [
                16,
                24,
                14
            ]
        },
        "16": {
            "pos": [
                10.8458744188015,
                52.741915067849284
            ],
            "adj": [
                31,
                24,
                15
            ]
        },
        "17": {
            "pos": [
                10.796496898831283,
                51.72921313983424
            ],
            "adj": [
                27,
                30,
                26,
                19,
                2,
                5
            ]
        },
        "18": {
            "pos": [
                10.699166511392963,
                52.33105613121614
            ],
            "adj": [
                23,
                12,
                14
            ]
        },
        "19": {
            "pos": [
                10.75098195777885,
                51.65948781090508
            ],
            "adj": [
                17,
                26,
                2
            ]
        },
        "20": {
            "pos": [
                10.838760143200119,
                52.26746115714596
            ],
            "adj": [
                23,
                32,
                34,
                11,
                12
            ]
        },
        "21": {
            "pos": [
                10.827033368534996,
                52.07208103314755
            ],
            "adj": [
                9,
                11,
                29,
                25
            ]
        },
        "22": {
            "pos": [
                10.831455736536146,
                51.2609510237643
            ],
            "adj": [
                1,
                28,
                0
            ]
        },
        "23": {
            "pos": [
                10.845201445430693,
                52.36418029302754
            ],
            "adj": [
                14,
                24,
                32,
                20,
                18
            ]
        },
        "24": {
            "pos": [
                10.845867231111322,
                52.5068165185859
            ],
            "adj": [
                16,
                31,
                23,
                15
            ]
        },
        "25": {
            "pos": [
                10.890390561366951,
                51.8933076339097
            ],
            "adj": [
                9,
                21,
                29,
                33,
                27
            ]
        },
        "26": {
            "pos": [
                11.077859207599968,
                51.55305043961028
            ],
            "adj": [
                19,
                17,
                30,
                42,
                50,
                35,
                28,
                2
            ]
        },
        "27": {
            "pos": [
                10.86242483633886,
                51.80618318067567
            ],
            "adj": [
                25,
                30,
                17,
                5
            ]
        },
        "28": {
            "pos": [
                10.974791863147907,
                51.349534981330585
            ],
            "adj": [
                26,
                35,
                38,
                22,
                1
            ]
        },
        "29": {
            "pos": [
                11.002541278150725,
                52.03390679023543
            ],
            "adj": [
                21,
                11,
                34,
                36,
                39,
                41,
                33,
                25
            ]
        },
        "30": {
            "pos": [
                11.103536912764092,
                51.73633297607574
            ],
            "adj": [
                27,
                33,
                40,
                52,
                42,
                26,
                17
            ]
        },
        "31": {
            "pos": [
                11.126483403774357,
                52.60147928954496
            ],
            "adj": [
                16,
                46,
                32,
                24
            ]
        },
        "32": {
            "pos": [
                11.219527848209916,
                52.366609304134755
            ],
            "adj": [
                31,
                46,
                54,
                49,
                48,
                37,
                36,
                34,
                20,
                23
            ]
        },
        "33": {
            "pos": [
                11.035018287613154,
                51.84668446226129
            ],
            "adj": [
                29,
                41,
                40,
                30,
                25
            ]
        },
        "34": {
            "pos": [
                11.013486914246226,
                52.228285475861426
            ],
            "adj": [
                20,
                32,
                36,
                29,
                11
            ]
        },
        "35": {
            "pos": [
                11.177890203754627,
                51.39820031995743
            ],
            "adj": [
                28,
                26,
                50,
                45,
                43,
                38
            ]
        },
        "36": {
            "pos": [
                11.137767632605337,
                52.179540333594424
            ],
            "adj": [
                34,
                32,
                37,
                47,
                39,
                29
            ]
        },
        "37": {
            "pos": [
                11.205935583024155,
                52.21112983381613
            ],
            "adj": [
                36,
                32,
                48
            ]
        },
        "38": {
            "pos": [
                11.137709917596748,
                51.24551892219519
            ],
            "adj": [
                28,
                35,
                43,
                44
            ]
        },
        "39": {
            "pos": [
                11.229540398751864,
                52.08407900048394
            ],
            "adj": [
                36,
                47,
                41,
                29
            ]
        },
        "40": {
            "pos": [
                11.289390360881283,
                51.86482084858462
            ],
            "adj": [
                41,
                53,
                52,
                30,
                33
            ]
        },
        "41": {
            "pos": [
                11.285765799692907,
                51.98830430884963
            ],
            "adj": [
                39,
                47,
                53,
                40,
                33,
                29
            ]
        },
        "42": {
            "pos": [
                11.311852220541166,
                51.6690006689557
            ],
            "adj": [
                30,
                52,
                55,
                50,
                26
            ]
        },
        "43": {
            "pos": [
                11.202873628208476,
                51.28414856569399
            ],
            "adj": [
                35,
                45,
                38
            ]
        },
        "44": {
            "pos": [
                11.19418154536688,
                51.22900160220934
            ],
            "adj": [
                45,
                38
            ]
        },
        "45": {
            "pos": [
                11.414875049584218,
                51.32017355849026
            ],
            "adj": [
                35,
                50,
                60,
                63,
                44,
                43
            ]
        },
        "46": {
            "pos": [
                11.542278317948725,
                52.677822503935474
            ],
            "adj": [
                70,
                54,
                32,
                31
            ]
        },
        "47": {
            "pos": [
                11.413027585557986,
                52.11824150500806
            ],
            "adj": [
                36,
                48,
                49,
                51,
                57,
                56,
                41,
                39
            ]
        },
        "48": {
            "pos": [
                11.303022554242311,
                52.19925711075131
            ],
            "adj": [
                37,
                32,
                49,
                47
            ]
        },
        "49": {
            "pos": [
                11.432506213372044,
                52.221980627353794
            ],
            "adj": [
                32,
                54,
                61,
                51,
                47,
                48
            ]
        },
        "50": {
            "pos": [
                11.46286343762186,
                51.50534536123762
            ],
            "adj": [
                26,
                42,
                55,
                58,
                45,
                35
            ]
        },
        "51": {
            "pos": [
                11.44409353285903,
                52.17369966892759
            ],
            "adj": [
                47,
                49,
                59
            ]
        },
        "52": {
            "pos": [
                11.432767423510603,
                51.76660364157842
            ],
            "adj": [
                40,
                55,
                42,
                30
            ]
        },
        "53": {
            "pos": [
                11.562368840294647,
                51.89570115228563
            ],
            "adj": [
                41,
                56,
                67,
                55,
                40
            ]
        },
        "54": {
            "pos": [
                11.757034062068062,
                52.39837617238296
            ],
            "adj": [
                46,
                70,
                86,
                76,
                73,
                65,
                64,
                61,
                49,
                32
            ]
        },
        "55": {
            "pos": [
                11.694175457252154,
                51.61649201507001
            ],
            "adj": [
                42,
                52,
                53,
                68,
                85,
                81,
                75,
                58,
                50
            ]
        },
        "56": {
            "pos": [
                11.578118470746544,
                52.02770348227477
            ],
            "adj": [
                47,
                62,
                53
            ]
        },
        "57": {
            "pos": [
                11.571027139172275,
                52.111541443058854
            ],
            "adj": [
                47,
                59,
                62
            ]
        },
        "58": {
            "pos": [
                11.71447893859037,
                51.44838785464579
            ],
            "adj": [
                50,
                55,
                75,
                60
            ]
        },
        "59": {
            "pos": [
                11.585247031535115,
                52.15607872214861
            ],
            "adj": [
                51,
                61,
                64,
                65,
                57
            ]
        },
        "60": {
            "pos": [
                11.788798851951949,
                51.326969115046175
            ],
            "adj": [
                63,
                45,
                58,
                75,
                78,
                72
            ]
        },
        "61": {
            "pos": [
                11.559623882924909,
                52.182882569121084
            ],
            "adj": [
                49,
                54,
                59
            ]
        },
        "62": {
            "pos": [
                11.701297135521687,
                52.06783294903092
            ],
            "adj": [
                56,
                57,
                65,
                69,
                71,
                67
            ]
        },
        "63": {
            "pos": [
                11.638268770706688,
                51.27391502422708
            ],
            "adj": [
                60,
                72,
                66,
                45
            ]
        },
        "64": {
            "pos": [
                11.611175537109375,
                52.1755598895405
            ],
            "adj": [
                54,
                65,
                59
            ]
        },
        "65": {
            "pos": [
                11.702051045574706,
                52.181545428169265
            ],
            "adj": [
                54,
                69,
                62,
                59,
                64
            ]
        },
        "66": {
            "pos": [
                11.667766819207532,
                51.21887579403224
            ],
            "adj": [
                63
            ]
        },
        "67": {
            "pos": [
                11.882405826744076,
                51.912645163922555
            ],
            "adj": [
                53,
                62,
                71,
                74,
                84,
                83,
                68
            ]
        },
        "68": {
            "pos": [
                11.936426700976591,
                51.6656432476585
            ],
            "adj": [
                55,
                67,
                83,
                94,
                89
            ]
        },
        "69": {
            "pos": [
                11.841200493155917,
                52.17256553133063
            ],
            "adj": [
                65,
                73,
                77,
                71,
                62
            ]
        },
        "70": {
            "pos": [
                11.929052769395275,
                52.70635015017163
            ],
            "adj": [
                46,
                87,
                54
            ]
        },
        "71": {
            "pos": [
                11.84473579937199,
                52.11471850251659
            ],
            "adj": [
                62,
                69,
                74,
                67
            ]
        },
        "72": {
            "pos": [
                11.869404995814865,
                51.22970175548771
            ],
            "adj": [
                78,
                63,
                60
            ]
        },
        "73": {
            "pos": [
                11.853862259920138,
                52.242536398940395
            ],
            "adj": [
                54,
                76,
                69
            ]
        },
        "74": {
            "pos": [
                12.216615177874802,
                52.01596610784626
            ],
            "adj": [
                67,
                71,
                77,
                122,
                119,
                98,
                84
            ]
        },
        "75": {
            "pos": [
                11.934403807534284,
                51.40534427346308
            ],
            "adj": [
                58,
                55,
                82,
                79,
                80,
                60
            ]
        },
        "76": {
            "pos": [
                12.072968881249867,
                52.28435887410336
            ],
            "adj": [
                86,
                77,
                73,
                54
            ]
        },
        "77": {
            "pos": [
                12.168700329835564,
                52.170384718585865
            ],
            "adj": [
                69,
                76,
                86,
                107,
                122,
                74
            ]
        },
        "78": {
            "pos": [
                12.006295097466074,
                51.234781297200904
            ],
            "adj": [
                60,
                80,
                88,
                72
            ]
        },
        "79": {
            "pos": [
                12.07306667944069,
                51.395232466028396
            ],
            "adj": [
                75,
                82,
                85,
                92,
                80
            ]
        },
        "80": {
            "pos": [
                12.066794512033615,
                51.307222394369354
            ],
            "adj": [
                75,
                79,
                90,
                88,
                78
            ]
        },
        "81": {
            "pos": [
                12.000735308183076,
                51.48561731972674
            ],
            "adj": [
                55,
                85,
                82
            ]
        },
        "82": {
            "pos": [
                11.989279248653643,
                51.45919092732581
            ],
            "adj": [
                75,
                81,
                79
            ]
        },
        "83": {
            "pos": [
                12.13210502493999,
                51.72837677787821
            ],
            "adj": [
                68,
                67,
                84,
                98,
                101,
                96
            ]
        },
        "84": {
            "pos": [
                12.124019410713395,
                51.8541898072721
            ],
            "adj": [
                67,
                74,
                98,
                83
            ]
        },
        "85": {
            "pos": [
                12.085579234331771,
                51.453515612884665
            ],
            "adj": [
                79,
                81,
                55,
                89,
                93
            ]
        },
        "86": {
            "pos": [
                12.300913199196682,
                52.42301987776084
            ],
            "adj": [
                54,
                87,
                111,
                131,
                107,
                77,
                76
            ]
        },
        "87": {
            "pos": [
                12.196323605059964,
                52.690039403162
            ],
            "adj": [
                70,
                112,
                86
            ]
        },
        "88": {
            "pos": [
                12.177247728868538,
                51.22991571709503
            ],
            "adj": [
                80,
                90,
                91,
                104,
                78
            ]
        },
        "89": {
            "pos": [
                12.146515649212306,
                51.48870347113605
            ],
            "adj": [
                85,
                68,
                95
            ]
        },
        "90": {
            "pos": [
                12.151590521176221,
                51.285085492163496
            ],
            "adj": [
                92,
                97,
                91,
                88,
                80
            ]
        },
        "91": {
            "pos": [
                12.201641883201475,
                51.26420411713052
            ],
            "adj": [
                99,
                103,
                88,
                90
            ]
        },
        "92": {
            "pos": [
                12.278975361975506,
                51.36881330549489
            ],
            "adj": [
                79,
                93,
                110,
                116,
                113,
                99,
                97,
                90
            ]
        },
        "93": {
            "pos": [
                12.269362034503274,
                51.40506021769618
            ],
            "adj": [
                85,
                95,
                110,
                92
            ]
        },
        "94": {
            "pos": [
                12.23370766651283,
                51.60741176634286
            ],
            "adj": [
                68,
                96,
                102,
                106,
                105,
                100,
                95
            ]
        },
        "95": {
            "pos": [
                12.276206443785757,
                51.47721060404743
            ],
            "adj": [
                89,
                94,
                100,
                108,
                118,
                110,
                93
            ]
        },
        "96": {
            "pos": [
                12.236340000192419,
                51.6786610227539
            ],
            "adj": [
                83,
                102,
                94
            ]
        },
        "97": {
            "pos": [
                12.243264648076783,
                51.33130746950369
            ],
            "adj": [
                92,
                99,
                90
            ]
        },
        "98": {
            "pos": [
                12.296209930202378,
                51.85972716646191
            ],
            "adj": [
                74,
                109,
                101,
                83,
                84
            ]
        },
        "99": {
            "pos": [
                12.290640157320944,
                51.31189035135431
            ],
            "adj": [
                92,
                113,
                103,
                91,
                97
            ]
        },
        "100": {
            "pos": [
                12.274397344982974,
                51.5576906393661
            ],
            "adj": [
                94,
                105,
                108,
                95
            ]
        },
        "101": {
            "pos": [
                12.26110549491182,
                51.80322845683139
            ],
            "adj": [
                98,
                102,
                83
            ]
        },
        "102": {
            "pos": [
                12.341037674630687,
                51.71618104509271
            ],
            "adj": [
                101,
                109,
                120,
                105,
                106,
                94,
                96
            ]
        },
        "103": {
            "pos": [
                12.33415801522055,
                51.27991760406257
            ],
            "adj": [
                113,
                114,
                104,
                91,
                99
            ]
        },
        "104": {
            "pos": [
                12.324724120815803,
                51.23416456835586
            ],
            "adj": [
                103,
                115,
                88
            ]
        },
        "105": {
            "pos": [
                12.41747703929792,
                51.58742823639996
            ],
            "adj": [
                94,
                106,
                102,
                120,
                124,
                129,
                128,
                118,
                108,
                100
            ]
        },
        "106": {
            "pos": [
                12.306460362604804,
                51.6195843518592
            ],
            "adj": [
                102,
                105,
                94
            ]
        },
        "107": {
            "pos": [
                12.488061788020154,
                52.22592911293604
            ],
            "adj": [
                77,
                86,
                130,
                122
            ]
        },
        "108": {
            "pos": [
                12.419962336628569,
                51.50509891926468
            ],
            "adj": [
                95,
                100,
                105,
                118
            ]
        },
        "109": {
            "pos": [
                12.481655876391022,
                51.81984929016083
            ],
            "adj": [
                98,
                119,
                123,
                124,
                120,
                102
            ]
        },
        "110": {
            "pos": [
                12.360594767802384,
                51.39497425482139
            ],
            "adj": [
                93,
                95,
                116,
                92
            ]
        },
        "111": {
            "pos": [
                12.521107482181499,
                52.553250788759584
            ],
            "adj": [
                112,
                127,
                131,
                86
            ]
        },
        "112": {
            "pos": [
                12.449593380207277,
                52.71462435085158
            ],
            "adj": [
                127,
                111,
                87
            ]
        },
        "113": {
            "pos": [
                12.384701989009756,
                51.32566527244667
            ],
            "adj": [
                92,
                117,
                114,
                103,
                99
            ]
        },
        "114": {
            "pos": [
                12.410703052726022,
                51.28118504419471
            ],
            "adj": [
                113,
                117,
                115,
                103
            ]
        },
        "115": {
            "pos": [
                12.532378490452622,
                51.25206625402627
            ],
            "adj": [
                117,
                126,
                104,
                114
            ]
        },
        "116": {
            "pos": [
                12.42024191985461,
                51.37618460805677
            ],
            "adj": [
                110,
                118,
                121,
                117,
                92
            ]
        },
        "117": {
            "pos": [
                12.468338751622024,
                51.315533160622635
            ],
            "adj": [
                113,
                116,
                121,
                125,
                126,
                115,
                114
            ]
        },
        "118": {
            "pos": [
                12.515309260225573,
                51.46024615822648
            ],
            "adj": [
                108,
                105,
                128,
                125,
                116,
                95
            ]
        },
        "119": {
            "pos": [
                12.439415797457437,
                51.906241360783255
            ],
            "adj": [
                74,
                123,
                109
            ]
        },
        "120": {
            "pos": [
                12.48519916341149,
                51.66849878383897
            ],
            "adj": [
                102,
                109,
                124,
                105
            ]
        },
        "121": {
            "pos": [
                12.462176577192437,
                51.35791211664029
            ],
            "adj": [
                125,
                117,
                116
            ]
        },
        "122": {
            "pos": [
                12.536819044620387,
                52.066308901755114
            ],
            "adj": [
                74,
                77,
                107,
                130,
                123
            ]
        },
        "123": {
            "pos": [
                12.557193188187865,
                51.93839000456167
            ],
            "adj": [
                122,
                109,
                119
            ]
        },
        "124": {
            "pos": [
                12.566610215843072,
                51.71609697264566
            ],
            "adj": [
                120,
                109,
                129,
                105
            ]
        },
        "125": {
            "pos": [
                12.569602005953106,
                51.389658221756186
            ],
            "adj": [
                132,
                126,
                117,
                121,
                118
            ]
        },
        "126": {
            "pos": [
                12.576394302855123,
                51.333055230937525
            ],
            "adj": [
                117,
                125,
                115
            ]
        },
        "127": {
            "pos": [
                12.600154664717044,
                52.75744147047988
            ],
            "adj": [
                111,
                112
            ]
        },
        "128": {
            "pos": [
                12.606207464350819,
                51.535371000049906
            ],
            "adj": [
                105,
                129,
                132,
                118
            ]
        },
        "129": {
            "pos": [
                12.612674448572958,
                51.64379584344267
            ],
            "adj": [
                124,
                128,
                105
            ]
        },
        "130": {
            "pos": [
                12.615153822439488,
                52.25336588070606
            ],
            "adj": [
                131,
                122,
                107
            ]
        },
        "131": {
            "pos": [
                12.613645374896265,
                52.379160559217134
            ],
            "adj": [
                86,
                111,
                130
            ]
        },
        "132": {
            "pos": [
                12.623866239040023,
                51.439504136668916
            ],
            "adj": [
                128,
                125
            ]
        }
    }
}